{
  "name": "retrieval_goal-0005.json",
  "ceilingMaterial": "AI2-THOR/Materials/Wood/WoodFloorsCross",
  "floorMaterial": "UnityAssetStore/Kindergarten_Interior/Models/Materials/color wood 4",
  "wallMaterial": "AI2-THOR/Materials/Wood/WoodFloorsCross",
  "performerStart": {
    "position": {
      "x": -0.05,
      "y": 0,
      "z": -1.58
    },
    "rotation": {
      "y": 270
    }
  },
  "objects": [
    {
      "id": "eb7da71d-5f60-43fa-818c-8190c9e1da1d",
      "type": "crayon_blue",
      "info": ["tiny","light","wax","blue","crayon","tiny light wax blue crayon"],
      "mass": 0.125,
      "dimensions": {
        "x": 0.01,
        "y": 0.085,
        "z": 0.01
      },
      "moveable": true,
      "pickupable": true,
      "shows": [
        {
          "rotation": {
            "x": 0,
            "y": 180,
            "z": 0
          },
          "position": {
            "x": 1.76,
            "y": 0.01,
            "z": -0.59
          },
          "bounding_box": [
            {
              "x": 1.75,
              "y": 0,
              "z": -0.6
            },
            {
              "x": 1.75,
              "y": 0,
              "z": -0.58
            },
            {
              "x": 1.77,
              "y": 0,
              "z": -0.58
            },
            {
              "x": 1.77,
              "y": 0,
              "z": -0.6
            }
          ],
          "stepBegin": 0,
          "scale": {
            "x": 1,
            "y": 1,
            "z": 1
          }
        }
      ],
      "salientMaterials": ["wax"]
    },
    {
      "id": "wall_26c24c3a-2cbf-4e67-96dc-f60dbfe57d40",
      "materials": ["AI2-THOR/Materials/Wood/WoodFloorsCross"],
      "type": "cube",
      "kinematic": "true",
      "structure": "true",
      "mass": 100,
      "shows": [
        {
          "stepBegin": 0,
          "scale": {
            "x": 1.54,
            "y": 3,
            "z": 0.1
          },
          "rotation": {
            "x": 0,
            "y": 90,
            "z": 0
          },
          "position": {
            "x": 4.29,
            "y": 1.5,
            "z": -4.47
          },
          "bounding_box": [
            {
              "x": 4.19,
              "y": 0,
              "z": -2.9299999999999997
            },
            {
              "x": 4.39,
              "y": 0,
              "z": -2.9299999999999997
            },
            {
              "x": 4.39,
              "y": 0,
              "z": -6.01
            },
            {
              "x": 4.19,
              "y": 0,
              "z": -6.01
            }
          ]
        }
      ]
    },
    {
      "id": "wall_8086c657-3204-4546-afce-cc170bac66f1",
      "materials": ["AI2-THOR/Materials/Wood/WoodFloorsCross"],
      "type": "cube",
      "kinematic": "true",
      "structure": "true",
      "mass": 100,
      "shows": [
        {
          "stepBegin": 0,
          "scale": {
            "x": 2.17,
            "y": 3,
            "z": 0.1
          },
          "rotation": {
            "x": 0,
            "y": 90,
            "z": 0
          },
          "position": {
            "x": -1.59,
            "y": 1.5,
            "z": 3.58
          },
          "bounding_box": [
            {
              "x": -1.69,
              "y": 0,
              "z": 5.75
            },
            {
              "x": -1.4899999999999998,
              "y": 0,
              "z": 5.75
            },
            {
              "x": -1.4900000000000002,
              "y": 0,
              "z": 1.4100000000000001
            },
            {
              "x": -1.6900000000000004,
              "y": 0,
              "z": 1.4100000000000001
            }
          ]
        }
      ]
    },
    {
      "id": "wall_3b91477d-ba54-48e9-9add-72f815bcf6d1",
      "materials": ["AI2-THOR/Materials/Wood/WoodFloorsCross"],
      "type": "cube",
      "kinematic": "true",
      "structure": "true",
      "mass": 100,
      "shows": [
        {
          "stepBegin": 0,
          "scale": {
            "x": 2.17,
            "y": 3,
            "z": 0.1
          },
          "rotation": {
            "x": 0,
            "y": 270,
            "z": 0
          },
          "position": {
            "x": -2.7,
            "y": 1.5,
            "z": 2.93
          },
          "bounding_box": [
            {
              "x": -2.6000000000000005,
              "y": 0,
              "z": 0.7600000000000002
            },
            {
              "x": -2.8000000000000007,
              "y": 0,
              "z": 0.7600000000000002
            },
            {
              "x": -2.8,
              "y": 0,
              "z": 5.1
            },
            {
              "x": -2.5999999999999996,
              "y": 0,
              "z": 5.1
            }
          ]
        }
      ]
    }
  ],
  "goal": {
    "category": "retrieval",
    "domain_list": ["objects","places","object_solidity","navigation","localization"],
    "type_list": ["interaction","action_full","retrieve"],
    "task_list": ["navigate","localize","retrieve"],
    "info_list": ["tiny","light","wax","blue","crayon","tiny light wax blue crayon"],
    "metadata": {
      "target": {
        "id": "eb7da71d-5f60-43fa-818c-8190c9e1da1d",
        "info": ["tiny","light","wax","blue","crayon","tiny light wax blue crayon"],
        "match_image": true,
        "image": "[[[255,255,255],[255,255,255],[255,255,255],[255,255,255],[255,255,255],[210,215,225],[156,178,216],[170,192,229],[219,225,236],[255,255,255],[255,255,255],[255,255,255],[255,255,255],[255,255,255]],[[255,255,255],[255,255,255],[255,255,255],[255,255,255],[255,255,255],[154,167,190],[93,126,179],[114,146,203],[175,189,214],[255,255,255],[255,255,255],[255,255,255],[255,255,255],[255,255,255]],[[255,255,255],[255,255,255],[255,255,255],[255,255,255],[245,246,248],[97,119,156],[109,141,194],[123,153,206],[138,160,198],[250,251,253],[255,255,255],[255,255,255],[255,255,255],[255,255,255]],[[255,255,255],[255,255,255],[255,255,255],[255,255,255],[245,247,248],[85,110,150],[112,144,199],[122,153,207],[121,144,187],[248,249,251],[255,255,255],[255,255,255],[255,255,255],[255,255,255]],[[255,255,255],[255,255,255],[255,255,255],[255,255,255],[207,213,223],[76,103,149],[108,140,196],[116,148,204],[109,135,183],[225,231,243],[255,255,255],[255,255,255],[255,255,255],[255,255,255]],[[255,255,255],[255,255,255],[255,255,255],[255,255,255],[161,173,193],[65,96,145],[114,146,201],[122,152,206],[99,126,177],[188,200,221],[255,255,255],[255,255,255],[255,255,255],[255,255,255]],[[255,255,255],[255,255,255],[255,255,255],[254,254,255],[156,169,191],[70,101,152],[114,147,202],[118,150,203],[96,124,173],[181,193,215],[255,255,255],[255,255,255],[255,255,255],[255,255,255]],[[255,255,255],[255,255,255],[255,255,255],[245,246,248],[90,112,149],[76,107,157],[112,146,200],[114,148,202],[96,127,175],[132,155,192],[250,252,253],[255,255,255],[255,255,255],[255,255,255]],[[255,255,255],[255,255,255],[255,255,255],[246,247,248],[81,106,145],[79,111,161],[113,147,202],[116,150,203],[101,131,180],[116,140,181],[249,250,251],[255,255,255],[255,255,255],[255,255,255]],[[255,255,255],[255,255,255],[255,255,255],[206,212,222],[72,98,140],[82,115,165],[112,147,202],[115,149,202],[101,133,183],[107,134,178],[223,230,241],[255,255,255],[255,255,255],[255,255,255]],[[255,255,255],[255,255,255],[255,255,255],[164,176,195],[59,89,134],[84,118,168],[109,146,201],[110,147,201],[101,134,184],[93,121,169],[188,200,220],[255,255,255],[255,255,255],[255,255,255]],[[255,255,255],[255,255,255],[251,252,252],[129,146,174],[61,92,139],[85,119,170],[111,146,202],[113,148,204],[104,136,188],[92,120,167],[162,179,207],[253,254,255],[255,255,255],[255,255,255]],[[255,255,255],[255,255,255],[245,246,248],[84,107,144],[66,97,144],[85,120,171],[110,146,201],[116,150,206],[108,139,192],[95,124,172],[127,151,190],[249,251,253],[255,255,255],[255,255,255]],[[255,255,255],[255,255,255],[239,241,244],[80,104,141],[68,98,145],[88,120,171],[111,145,199],[115,148,203],[106,138,190],[97,125,175],[115,139,179],[244,246,250],[255,255,255],[255,255,255]],[[255,255,255],[255,255,255],[178,189,205],[63,90,131],[72,100,147],[90,122,173],[112,146,200],[113,147,201],[104,136,188],[97,125,174],[101,127,172],[203,214,232],[255,255,255],[255,255,255]],[[255,255,255],[255,255,255],[167,178,196],[58,86,128],[73,101,148],[93,125,176],[114,148,201],[116,150,203],[106,138,190],[99,128,176],[93,121,167],[189,200,219],[255,255,255],[255,255,255]],[[255,255,255],[251,252,252],[131,147,173],[62,89,132],[74,104,151],[93,125,177],[118,152,204],[125,159,210],[114,145,195],[100,131,179],[92,121,168],[159,177,206],[253,253,254],[255,255,255]],[[255,255,255],[245,246,249],[87,108,143],[65,92,135],[74,103,151],[92,124,175],[117,149,203],[122,156,207],[110,143,194],[100,131,179],[92,121,168],[121,146,186],[248,250,252],[255,255,255]],[[255,255,255],[244,246,248],[86,107,141],[71,97,138],[77,107,153],[92,124,173],[109,142,193],[115,148,199],[109,140,190],[103,132,182],[97,125,172],[115,139,179],[247,248,251],[255,255,255]],[[239,244,249],[136,153,179],[77,98,131],[87,111,148],[84,114,160],[88,118,166],[96,127,176],[104,132,182],[102,126,178],[104,126,179],[113,134,180],[104,127,170],[161,178,206],[245,250,252]],[[173,182,197],[53,77,116],[59,85,127],[62,91,134],[69,99,145],[77,109,158],[85,118,168],[88,121,171],[84,118,168],[85,117,164],[83,113,158],[83,109,153],[85,110,154],[187,199,215]],[[169,178,192],[67,86,122],[79,99,138],[84,107,146],[92,116,158],[101,125,170],[102,126,170],[102,126,171],[102,125,172],[102,127,172],[100,125,168],[97,119,161],[91,113,154],[181,191,208]],[[173,179,193],[87,100,132],[101,115,150],[104,120,157],[107,124,163],[111,130,171],[114,133,176],[115,134,179],[116,136,179],[117,136,178],[117,135,175],[114,131,168],[101,117,153],[178,186,201]],[[172,178,191],[86,99,129],[98,111,142],[99,114,146],[101,116,150],[106,122,159],[109,125,163],[111,127,166],[111,128,167],[111,128,165],[112,127,163],[110,126,160],[98,113,147],[175,182,196]],[[170,176,188],[78,88,108],[88,98,119],[87,98,120],[89,101,123],[91,101,121],[94,103,125],[95,105,127],[96,106,128],[99,111,137],[99,111,135],[101,113,138],[89,102,128],[172,179,192]],[[170,176,187],[82,94,120],[94,107,135],[97,110,141],[100,115,148],[106,122,160],[110,127,166],[112,129,168],[111,128,167],[109,126,161],[109,125,158],[106,121,153],[92,106,135],[173,179,193]],[[170,176,187],[81,94,120],[93,105,133],[96,108,138],[98,111,143],[100,114,145],[103,118,150],[104,120,152],[106,121,153],[107,123,156],[108,123,155],[105,118,149],[92,106,135],[173,180,193]],[[170,176,189],[83,96,124],[97,111,141],[99,115,147],[101,118,154],[106,123,161],[110,129,169],[110,130,170],[112,131,170],[112,130,167],[111,127,163],[107,123,154],[95,110,141],[174,181,195]],[[172,179,192],[86,101,131],[99,116,149],[102,120,155],[105,124,162],[108,129,169],[112,132,173],[112,133,176],[113,134,176],[114,134,175],[114,133,171],[111,130,166],[99,116,150],[176,184,198]],[[173,180,193],[86,101,131],[98,115,147],[102,120,156],[106,125,164],[110,130,170],[112,133,174],[113,134,176],[113,134,176],[114,133,174],[114,133,171],[112,130,166],[99,116,150],[177,185,199]],[[173,180,193],[86,100,130],[97,113,146],[102,120,156],[105,124,163],[109,129,170],[113,132,174],[112,132,174],[113,134,175],[114,134,174],[113,132,171],[111,128,165],[98,115,149],[177,185,199]],[[173,180,193],[85,100,130],[97,112,145],[100,117,154],[104,123,160],[106,125,165],[110,129,170],[113,133,175],[114,135,177],[115,136,176],[114,133,171],[110,128,164],[98,114,148],[177,185,199]],[[173,179,193],[85,100,129],[97,112,144],[100,117,153],[104,122,160],[106,127,166],[110,130,170],[112,133,175],[113,134,175],[115,134,175],[113,132,170],[109,128,164],[97,114,148],[176,184,198]],[[173,179,193],[86,100,130],[97,113,145],[99,116,151],[103,122,160],[106,125,164],[109,129,169],[110,131,172],[112,132,173],[112,131,172],[112,130,168],[109,127,163],[97,114,147],[176,184,198]],[[173,180,193],[86,101,131],[97,114,147],[99,117,151],[103,121,159],[106,125,163],[110,129,169],[111,132,173],[112,132,174],[112,132,171],[111,130,167],[109,127,162],[97,114,147],[177,184,199]],[[173,180,193],[86,101,131],[97,114,146],[99,117,152],[103,122,159],[105,124,164],[108,127,167],[112,131,173],[113,133,175],[113,133,172],[111,130,168],[109,127,162],[97,114,148],[177,184,199]],[[173,180,193],[86,101,131],[97,113,146],[99,117,152],[103,122,158],[105,124,164],[107,126,166],[108,128,169],[111,131,172],[113,132,172],[112,131,169],[109,127,162],[97,114,147],[177,184,198]],[[173,179,193],[85,100,130],[97,113,146],[100,117,153],[103,121,158],[106,125,164],[109,128,167],[109,129,170],[109,129,170],[111,132,171],[113,131,169],[109,127,162],[97,114,148],[176,184,198]],[[173,179,193],[85,100,130],[97,113,146],[100,118,153],[103,121,159],[107,125,164],[110,128,169],[110,130,171],[110,130,171],[111,130,170],[112,130,168],[109,127,163],[97,114,148],[176,184,198]],[[173,179,192],[85,100,130],[97,112,145],[101,117,153],[104,122,160],[106,124,164],[108,127,168],[110,130,171],[110,130,171],[112,130,170],[112,129,167],[109,127,163],[97,114,148],[176,183,198]],[[173,179,192],[84,99,129],[97,112,145],[102,118,154],[106,123,161],[107,127,167],[107,129,168],[110,130,169],[111,131,172],[113,131,172],[112,130,168],[109,127,162],[97,114,147],[176,183,198]],[[173,179,192],[84,98,129],[97,113,145],[103,118,155],[102,118,154],[95,110,142],[91,103,129],[92,103,129],[97,110,139],[105,121,155],[111,128,166],[109,126,161],[96,113,146],[176,183,198]],[[173,178,192],[84,98,129],[97,112,145],[94,108,139],[80,92,115],[78,85,104],[79,87,105],[80,89,107],[81,90,108],[87,97,116],[100,113,143],[109,125,161],[97,113,147],[176,183,198]],[[173,178,192],[86,99,130],[94,107,138],[76,88,107],[70,81,96],[76,85,102],[78,87,106],[80,89,108],[81,91,110],[84,92,109],[87,94,113],[100,114,144],[97,113,148],[176,183,198]],[[173,179,192],[86,98,129],[81,92,115],[68,79,93],[69,81,96],[75,83,100],[78,86,105],[79,87,107],[81,91,108],[85,92,110],[85,91,108],[88,99,121],[95,110,144],[176,184,198]],[[173,180,194],[80,93,120],[73,81,96],[72,80,96],[77,87,107],[80,88,109],[79,86,104],[80,88,107],[84,92,111],[85,92,111],[85,92,109],[83,91,107],[87,99,126],[177,184,200]],[[172,179,194],[74,86,109],[73,77,91],[77,86,106],[91,105,136],[94,110,142],[82,90,109],[94,106,134],[100,117,151],[97,111,141],[90,97,119],[84,90,105],[82,91,113],[177,183,198]],[[171,179,193],[70,79,98],[72,77,91],[84,96,121],[87,99,126],[95,110,142],[95,111,142],[95,108,137],[87,101,125],[95,109,137],[98,110,138],[84,91,107],[78,86,104],[175,181,193]],[[170,178,191],[65,72,87],[73,79,94],[86,98,123],[86,97,121],[101,118,154],[97,113,146],[86,97,123],[100,118,153],[96,110,139],[97,110,138],[88,96,116],[76,83,99],[173,178,190]],[[169,176,188],[62,70,83],[73,79,93],[86,97,122],[86,95,119],[94,108,139],[82,94,118],[96,113,147],[95,110,140],[95,109,138],[95,107,135],[89,98,117],[75,81,98],[171,176,187]],[[168,173,184],[62,69,82],[71,76,90],[84,93,117],[89,101,128],[87,98,122],[98,114,144],[97,112,144],[92,105,133],[97,112,142],[97,110,138],[87,95,112],[74,81,97],[170,174,185]],[[167,171,181],[62,69,82],[71,76,90],[76,81,97],[88,100,126],[100,119,155],[96,113,144],[94,109,140],[98,115,148],[101,118,152],[99,114,144],[84,92,108],[73,81,97],[170,173,182]],[[166,169,178],[62,69,82],[71,77,90],[74,79,95],[88,100,126],[82,96,121],[83,97,122],[90,103,129],[89,100,125],[94,108,135],[99,114,143],[83,92,108],[72,80,96],[169,172,180]],[[165,168,175],[62,69,82],[71,77,90],[76,82,99],[87,98,124],[84,96,121],[94,110,142],[89,101,129],[93,108,138],[99,114,145],[94,107,132],[82,90,106],[72,79,95],[167,171,179]],[[164,166,173],[61,66,80],[70,75,89],[81,90,112],[87,100,128],[85,98,123],[96,110,140],[90,103,128],[92,105,133],[92,104,130],[85,91,110],[82,89,105],[72,79,96],[167,170,178]],[[164,166,173],[60,65,79],[71,77,92],[87,99,126],[87,100,128],[84,95,119],[90,101,127],[102,119,152],[92,108,138],[97,112,143],[86,93,113],[81,88,105],[72,78,95],[167,170,177]],[[163,166,172],[60,66,79],[70,75,89],[81,90,112],[90,105,135],[98,113,147],[101,116,152],[106,124,163],[99,118,153],[96,111,141],[85,92,110],[81,88,104],[72,78,94],[166,169,176]],[[163,166,172],[61,65,79],[72,77,91],[79,87,106],[88,100,126],[98,115,150],[93,106,135],[95,108,141],[100,117,153],[99,114,147],[87,97,118],[82,89,106],[72,79,95],[166,169,176]],[[163,165,172],[62,66,79],[74,81,97],[82,91,112],[92,104,133],[85,98,121],[90,106,133],[98,116,152],[91,104,133],[95,110,140],[91,103,129],[83,90,108],[73,79,95],[166,169,176]],[[163,165,171],[62,66,78],[71,76,88],[76,82,99],[89,101,128],[81,94,117],[96,114,148],[97,112,145],[100,118,153],[94,109,138],[91,103,128],[83,89,105],[72,79,94],[166,169,176]],[[163,165,171],[61,66,78],[72,76,89],[78,85,104],[91,105,134],[84,97,122],[97,114,149],[97,111,142],[102,120,155],[94,108,136],[92,103,127],[82,88,104],[71,78,95],[166,169,176]],[[163,165,171],[60,64,76],[75,81,98],[87,100,127],[95,111,145],[90,104,132],[88,102,129],[96,111,143],[90,103,129],[95,108,137],[90,100,123],[80,87,104],[71,78,95],[166,169,176]],[[163,165,171],[60,64,77],[76,84,103],[85,99,125],[88,101,129],[102,118,154],[96,112,145],[93,107,137],[95,110,141],[93,107,134],[84,91,109],[80,87,104],[71,78,95],[166,169,175]],[[163,165,172],[60,65,78],[71,77,92],[87,99,125],[92,106,137],[96,110,142],[95,108,139],[92,107,135],[99,115,148],[88,98,122],[82,89,104],[80,88,105],[71,78,94],[166,169,176]],[[163,165,172],[59,65,78],[70,76,92],[85,97,123],[92,105,136],[93,106,137],[94,108,138],[93,107,135],[100,116,151],[92,104,132],[83,91,108],[80,87,104],[71,77,94],[166,169,176]],[[163,165,171],[59,64,77],[75,81,100],[86,98,125],[90,103,132],[94,109,142],[97,113,147],[104,122,160],[96,111,143],[95,111,142],[88,98,120],[80,86,103],[71,77,94],[166,169,176]],[[163,165,171],[60,65,77],[73,79,95],[86,98,126],[94,110,143],[91,105,135],[86,99,124],[83,92,114],[89,101,127],[98,114,147],[89,98,121],[80,87,103],[71,77,94],[166,169,175]],[[163,165,172],[61,65,77],[75,82,99],[86,98,126],[84,96,123],[78,88,109],[85,96,122],[82,91,112],[99,114,148],[100,117,150],[90,100,122],[80,87,103],[71,77,94],[166,168,175]],[[163,165,172],[61,65,77],[78,87,108],[84,95,122],[80,89,114],[81,89,110],[83,92,114],[81,88,108],[84,93,115],[94,109,138],[94,106,132],[80,87,104],[70,77,94],[166,168,175]],[[163,166,172],[59,64,77],[73,80,97],[86,98,126],[92,104,137],[92,105,136],[93,107,137],[98,115,150],[88,101,127],[94,109,138],[88,98,121],[80,86,103],[71,76,93],[166,169,175]],[[163,166,172],[59,64,77],[70,75,92],[82,94,119],[91,103,134],[93,106,137],[94,109,141],[89,102,131],[84,96,120],[93,108,137],[83,91,109],[80,86,103],[71,76,93],[166,169,176]],[[163,166,173],[59,64,77],[74,81,99],[83,94,120],[79,91,114],[81,91,113],[86,98,123],[83,94,116],[101,120,157],[95,111,142],[87,96,118],[80,87,103],[72,78,94],[168,170,178]],[[163,166,173],[59,65,77],[74,83,101],[79,91,115],[86,101,129],[96,112,145],[83,92,114],[86,96,120],[93,108,138],[91,105,134],[92,105,133],[79,87,104],[72,79,94],[168,172,180]],[[164,168,175],[59,64,77],[74,83,100],[78,90,113],[80,92,117],[87,99,126],[84,95,117],[82,91,112],[88,99,125],[95,111,143],[88,100,124],[80,86,102],[71,78,93],[168,172,180]],[[166,170,179],[59,64,78],[72,81,97],[83,97,123],[83,97,124],[89,102,129],[96,111,140],[96,114,147],[102,121,156],[98,115,148],[91,103,128],[80,86,103],[70,77,93],[168,172,180]],[[168,173,183],[62,66,79],[70,75,89],[83,96,123],[91,106,138],[83,93,116],[78,86,105],[80,88,107],[95,110,142],[92,104,134],[93,105,134],[79,87,104],[70,77,93],[169,173,183]],[[169,175,186],[62,67,80],[71,75,89],[82,93,118],[87,101,131],[89,102,128],[78,85,102],[76,83,99],[88,101,128],[91,104,133],[93,105,134],[80,87,106],[71,77,94],[170,175,186]],[[171,176,189],[64,69,85],[71,75,89],[81,92,115],[81,92,116],[93,110,143],[83,94,117],[79,86,105],[91,105,135],[91,104,134],[92,103,131],[80,87,105],[72,79,97],[173,178,190]],[[172,177,190],[69,76,95],[70,73,85],[81,89,111],[84,94,119],[81,91,114],[90,103,133],[94,107,139],[90,102,130],[90,103,130],[89,100,126],[80,86,102],[75,82,101],[174,180,193]],[[172,178,191],[73,82,105],[70,73,85],[73,77,92],[84,94,118],[88,102,129],[87,97,122],[82,95,121],[88,101,127],[94,107,137],[81,91,111],[79,85,101],[79,87,109],[175,181,196]],[[171,176,190],[78,89,115],[72,77,91],[70,74,87],[71,76,90],[79,87,106],[89,101,126],[87,102,130],[87,102,129],[81,92,115],[76,84,103],[80,86,103],[84,97,123],[176,182,197]],[[170,176,189],[81,93,122],[76,85,105],[70,74,87],[72,76,90],[72,77,93],[73,80,95],[72,81,96],[72,80,98],[76,84,101],[80,86,103],[84,91,112],[92,106,137],[175,182,196]],[[170,176,189],[82,94,123],[86,98,124],[73,78,94],[71,75,89],[70,77,94],[73,80,96],[72,81,98],[75,83,101],[78,84,101],[81,87,103],[94,104,131],[93,108,140],[174,181,195]],[[171,176,189],[81,94,123],[92,105,136],[85,96,123],[74,81,99],[69,77,92],[72,80,97],[74,82,100],[76,84,99],[80,87,104],[91,102,126],[102,117,150],[92,107,139],[174,181,194]],[[171,176,189],[80,94,122],[92,105,136],[94,108,141],[90,104,133],[82,93,116],[78,86,105],[78,85,104],[83,94,117],[95,108,137],[103,119,153],[103,119,153],[91,107,138],[174,181,194]],[[170,176,190],[80,94,122],[91,105,135],[94,107,140],[96,111,146],[99,116,152],[100,116,152],[100,117,153],[103,121,158],[105,121,159],[104,120,156],[102,118,151],[92,107,139],[174,180,194]],[[171,177,190],[81,94,122],[91,105,135],[94,108,140],[95,110,144],[98,115,151],[100,119,156],[102,121,158],[102,121,158],[103,120,158],[104,119,155],[100,117,149],[89,105,136],[174,180,194]],[[171,177,190],[81,94,122],[91,105,135],[93,108,140],[94,109,143],[97,114,149],[100,118,154],[101,120,156],[102,121,157],[102,120,156],[104,120,155],[101,118,150],[90,105,136],[174,180,194]],[[171,177,190],[79,93,121],[90,104,133],[92,107,139],[94,109,143],[96,114,149],[100,118,154],[101,120,156],[101,120,156],[102,120,155],[102,120,154],[100,117,149],[89,105,135],[174,181,195]],[[171,177,189],[79,93,121],[90,104,133],[92,107,138],[93,109,142],[96,113,148],[99,118,153],[100,120,156],[101,120,156],[102,119,155],[102,119,153],[100,116,148],[89,105,136],[174,181,195]],[[170,176,189],[79,93,121],[91,104,134],[92,107,138],[93,110,143],[94,111,146],[98,116,152],[99,118,154],[101,119,155],[102,119,155],[102,118,153],[101,117,148],[91,106,137],[175,181,195]],[[170,176,189],[79,93,120],[91,105,136],[92,108,139],[93,109,143],[94,112,146],[98,116,152],[100,118,154],[101,118,155],[102,119,155],[102,119,153],[101,118,149],[91,107,138],[175,181,195]],[[171,177,189],[79,93,120],[91,105,135],[92,108,139],[94,111,144],[97,114,150],[99,117,153],[100,117,154],[100,118,154],[101,119,155],[102,119,153],[101,118,151],[91,107,138],[174,181,194]],[[171,177,190],[80,93,121],[90,105,134],[93,108,140],[95,111,145],[99,116,151],[101,119,155],[101,119,156],[100,118,154],[101,118,154],[102,119,153],[101,118,151],[90,106,137],[174,181,194]],[[171,177,189],[79,93,121],[90,104,133],[92,108,139],[94,110,144],[97,114,149],[100,118,154],[100,118,155],[101,119,155],[101,119,154],[102,118,153],[101,118,149],[90,106,137],[174,180,194]],[[170,176,189],[79,92,120],[89,103,132],[91,106,137],[93,109,142],[96,111,146],[98,115,152],[101,120,156],[103,122,159],[103,121,157],[102,119,153],[101,117,149],[90,105,136],[173,180,193]],[[170,176,189],[79,92,120],[89,103,131],[91,106,137],[93,109,142],[95,111,146],[98,115,151],[99,117,153],[100,118,154],[100,118,154],[101,119,152],[100,116,148],[89,104,135],[173,180,193]],[[171,176,189],[80,93,121],[89,103,132],[90,105,136],[92,108,141],[94,111,146],[97,115,150],[99,117,153],[99,117,152],[99,117,152],[100,117,151],[100,116,148],[89,104,135],[174,180,194]],[[171,176,188],[81,92,121],[90,104,133],[90,104,136],[92,108,141],[94,111,146],[97,115,151],[99,118,153],[100,118,154],[100,118,153],[100,117,151],[101,116,149],[90,105,137],[175,181,193]],[[170,175,187],[79,92,119],[90,103,133],[91,104,136],[94,108,142],[94,110,145],[95,112,148],[99,118,153],[100,119,155],[103,119,155],[103,119,153],[102,116,149],[90,104,135],[173,180,192]],[[168,174,186],[73,85,107],[84,95,119],[87,97,124],[89,102,131],[92,107,140],[93,109,142],[94,111,143],[95,112,145],[98,113,144],[99,113,142],[95,108,135],[85,98,124],[172,178,191]],[[170,176,187],[78,90,116],[86,98,124],[87,98,125],[87,99,127],[85,96,121],[87,98,123],[87,98,123],[89,101,127],[95,109,139],[97,112,140],[98,111,140],[89,103,132],[173,179,191]],[[172,178,189],[80,92,120],[90,102,132],[92,105,137],[94,107,140],[94,111,144],[98,115,149],[99,116,152],[99,116,152],[100,116,151],[102,117,151],[102,116,149],[90,105,138],[176,183,196]],[[172,178,189],[65,79,109],[72,88,121],[81,98,131],[88,105,139],[90,109,144],[92,111,148],[94,113,152],[92,112,150],[90,109,146],[88,106,142],[85,104,141],[82,101,139],[180,189,204]],[[171,177,189],[58,74,103],[62,80,113],[62,84,117],[63,86,121],[65,87,125],[66,91,131],[65,92,133],[67,93,133],[68,91,132],[67,89,129],[73,95,133],[77,99,136],[181,190,205]],[[167,173,186],[57,72,100],[63,81,110],[61,82,113],[59,82,117],[59,84,122],[62,88,126],[61,89,129],[64,89,130],[63,89,130],[64,90,129],[70,94,130],[74,96,132],[177,187,202]],[[207,210,217],[70,83,107],[57,74,103],[57,78,111],[57,80,115],[58,83,120],[62,87,126],[61,89,129],[63,90,131],[60,88,129],[61,88,127],[61,85,121],[84,104,136],[213,218,226]],[[255,255,255],[203,205,210],[100,108,126],[70,83,105],[60,75,102],[47,65,94],[46,65,96],[44,65,97],[45,65,97],[60,78,107],[71,87,112],[108,121,136],[210,213,217],[255,255,255]],[[255,255,255],[255,255,255],[250,250,250],[241,241,242],[206,206,210],[159,162,168],[159,162,169],[158,161,168],[165,167,173],[213,214,217],[241,241,241],[251,251,252],[255,255,255],[255,255,255]]]",
        "image_name": "crayon_blue.png"
      }
    },
    "description": "Find and pick up the tiny light wax blue crayon."
  },
  "answer": {}
}
